pyqtdeploy/__init__.py
pyqtdeploy/file_utilities.py
pyqtdeploy/message_handler.py
pyqtdeploy/parts.py
pyqtdeploy/platforms.py
pyqtdeploy/pyqtdeploy_main.py
pyqtdeploy/pyqtdeploybuild_main.py
pyqtdeploy/pyqtdeploysysroot_main.py
pyqtdeploy/user_exception.py
pyqtdeploy/version.py
pyqtdeploy/version_number.py
pyqtdeploy/builder/__init__.py
pyqtdeploy/builder/builder.py
pyqtdeploy/builder/lib/__init__.py
pyqtdeploy/builder/lib/freeze.py
pyqtdeploy/builder/lib/pdytools_module.cpp
pyqtdeploy/builder/lib/post_configuration.pro
pyqtdeploy/builder/lib/pyqtdeploy_start.cpp
pyqtdeploy/builder/lib/bootstrap/__init__.py
pyqtdeploy/builder/lib/bootstrap/bootstrap-3.10.0.py
pyqtdeploy/builder/lib/bootstrap/bootstrap-3.11.0.py
pyqtdeploy/builder/lib/bootstrap/bootstrap-3.7.0.py
pyqtdeploy/builder/lib/bootstrap/bootstrap-3.8.0.py
pyqtdeploy/builder/lib/bootstrap/bootstrap-3.9.0.py
pyqtdeploy/builder/lib/bootstrap_external/__init__.py
pyqtdeploy/builder/lib/bootstrap_external/bootstrap_external-3.10.0.py
pyqtdeploy/builder/lib/bootstrap_external/bootstrap_external-3.10.3.py
pyqtdeploy/builder/lib/bootstrap_external/bootstrap_external-3.11.0.py
pyqtdeploy/builder/lib/bootstrap_external/bootstrap_external-3.7.0.py
pyqtdeploy/builder/lib/bootstrap_external/bootstrap_external-3.8.0.py
pyqtdeploy/builder/lib/bootstrap_external/bootstrap_external-3.8.10.py
pyqtdeploy/builder/lib/bootstrap_external/bootstrap_external-3.8.11.py
pyqtdeploy/builder/lib/bootstrap_external/bootstrap_external-3.9.0.py
pyqtdeploy/builder/lib/bootstrap_external/bootstrap_external-3.9.11.py
pyqtdeploy/builder/lib/bootstrap_external/bootstrap_external-3.9.5.py
pyqtdeploy/builder/lib/bootstrap_external/bootstrap_external-3.9.6.py
pyqtdeploy/gui/__init__.py
pyqtdeploy/gui/application_page.py
pyqtdeploy/gui/better_form.py
pyqtdeploy/gui/collapsible_widget.py
pyqtdeploy/gui/exception_handlers.py
pyqtdeploy/gui/filename_editor.py
pyqtdeploy/gui/filename_editor_delegate.py
pyqtdeploy/gui/package_editor.py
pyqtdeploy-3.3.0.dist-info/METADATA
pyqtdeploy-3.3.0.dist-info/WHEEL
pyqtdeploy-3.3.0.dist-info/entry_points.txt
pyqtdeploy-3.3.0.dist-info/top_level.txt
pyqtdeploy-3.3.0.dist-info/RECORD
