Metadata-Version: 2.1
Name: pyqtdeploy
Version: 3.3.0
Summary: PyQt Application Deployment Tool
Home-page: https://www.riverbankcomputing.com/software/pyqtdeploy/
Author: Riverbank Computing Limited
Author-email: info@riverbankcomputing.com
License: BSD
Platform: X11
Platform: macOS
Platform: Windows
Requires-Python: >=3.7.0
Requires-Dist: PyQt5
Requires-Dist: toml
